{
  "components": {
    "requestBodies": {
      "OtpGenerateRequest": {
        "content": {
          "application/json": {
            "schema": {
              "$ref": "#/components/schemas/GenerateRequest"
            }
          }
        },
        "description": "OtpGenerateRequest"
      },
      "OtpValidateRequest": {
        "content": {
          "application/json": {
            "schema": {
              "$ref": "#/components/schemas/ValidateRequest"
            }
          }
        },
        "description": "OtpValidateRequest"
      }
    },
    "responses": {
      "MicroAPIError": {
        "content": {
          "application/json": {
            "schema": {
              "properties": {
                "Code": {
                  "description": "Error code",
                  "example": 500,
                  "type": "number"
                },
                "Detail": {
                  "description": "Error detail",
                  "example": "service not found",
                  "type": "string"
                },
                "Id": {
                  "description": "Error ID",
                  "type": "string"
                },
                "Status": {
                  "description": "Error status message",
                  "example": "Internal Server Error",
                  "type": "string"
                }
              },
              "title": "MicroAPIError",
              "type": "object"
            }
          }
        },
        "description": "Error from the Micro API"
      },
      "OtpGenerateResponse": {
        "content": {
          "application/json": {
            "schema": {
              "$ref": "#/components/schemas/GenerateResponse"
            }
          }
        },
        "description": "OtpGenerateResponse"
      },
      "OtpValidateResponse": {
        "content": {
          "application/json": {
            "schema": {
              "$ref": "#/components/schemas/ValidateResponse"
            }
          }
        },
        "description": "OtpValidateResponse"
      }
    },
    "schemas": {
      "GenerateRequest": {
        "description": "Generate an OTP (one time pass) code",
        "properties": {
          "expiry": {
            "description": "expiration in seconds (default: 60)",
            "format": "int64",
            "type": "number"
          },
          "id": {
            "description": "unique id, email or user to generate an OTP for",
            "type": "string"
          },
          "size": {
            "description": "number of characters (default: 6)",
            "format": "int64",
            "type": "number"
          }
        },
        "title": "GenerateRequest",
        "type": "object"
      },
      "GenerateResponse": {
        "properties": {
          "code": {
            "description": "one time pass code",
            "type": "string"
          }
        },
        "title": "GenerateResponse",
        "type": "object"
      },
      "ValidateRequest": {
        "description": "Validate the OTP code",
        "properties": {
          "code": {
            "description": "one time pass code to validate",
            "type": "string"
          },
          "id": {
            "description": "unique id, email or user for which the code was generated",
            "type": "string"
          }
        },
        "title": "ValidateRequest",
        "type": "object"
      },
      "ValidateResponse": {
        "properties": {
          "success": {
            "description": "returns true if the code is valid for the ID",
            "type": "boolean"
          }
        },
        "title": "ValidateResponse",
        "type": "object"
      }
    },
    "securitySchemes": {
      "M3OAPIToken": {
        "bearerFormat": "token",
        "description": "M3O API token",
        "scheme": "bearer",
        "type": "http"
      }
    }
  },
  "info": {
    "description": "Generated by protoc-gen-openapi",
    "title": "Otp",
    "version": "1",
    "x-logo": {
      "altText": "M3O logo",
      "backgroundColor": "#000000",
      "url": "https://raw.githubusercontent.com/m3o/m3o/main/images/logo.png"
    }
  },
  "openapi": "3.0.0",
  "paths": {
    "/otp/Otp/Generate": {
      "parameters": [
        {
          "in": "header",
          "name": "Micro-Namespace",
          "required": true,
          "schema": {
            "default": "micro",
            "type": "string"
          }
        }
      ],
      "post": {
        "requestBody": {
          "$ref": "#/components/requestBodies/OtpGenerateRequest"
        },
        "responses": {
          "200": {
            "$ref": "#/components/responses/OtpGenerateResponse"
          },
          "default": {
            "$ref": "#/components/responses/MicroAPIError"
          }
        },
        "security": [
          {
            "MicroAPIToken": []
          }
        ],
        "summary": "Otp.Generate(GenerateRequest)"
      }
    },
    "/otp/Otp/Validate": {
      "parameters": [
        {
          "in": "header",
          "name": "Micro-Namespace",
          "required": true,
          "schema": {
            "default": "micro",
            "type": "string"
          }
        }
      ],
      "post": {
        "requestBody": {
          "$ref": "#/components/requestBodies/OtpValidateRequest"
        },
        "responses": {
          "200": {
            "$ref": "#/components/responses/OtpValidateResponse"
          },
          "default": {
            "$ref": "#/components/responses/MicroAPIError"
          }
        },
        "security": [
          {
            "MicroAPIToken": []
          }
        ],
        "summary": "Otp.Validate(ValidateRequest)"
      }
    }
  },
  "servers": [
    {
      "url": "https://api.m3o.com/v1",
      "description": "M3O platform"
    }
  ]
}